LICENSE
MANIFEST.in
README
setup.cfg
setup.py
test.conf
test.ini
mongrel2_wsgi/__init__.py
mongrel2_wsgi/request.py
mongrel2_wsgi/runner.py
mongrel2_wsgi/server.py
mongrel2_wsgi/test_server.py
mongrel2_wsgi/wsgiserver.py
mongrel2_wsgi.egg-info/PKG-INFO
mongrel2_wsgi.egg-info/SOURCES.txt
mongrel2_wsgi.egg-info/dependency_links.txt
mongrel2_wsgi.egg-info/entry_points.txt
mongrel2_wsgi.egg-info/not-zip-safe
mongrel2_wsgi.egg-info/requires.txt
mongrel2_wsgi.egg-info/top_level.txt