Metadata-Version: 1.0
Name: mongrel2-wsgi
Version: 0.3dev
Summary: Mongrel2 handler to WSGI.
Home-page: http://bitbucket.org/dholth/mongrel2_wsgi
Author: Daniel Holth
Author-email: dholth@fastmail.fm
License: BSD
Keywords: wsgi mongrel2 eventlet
Platform: UNKNOWN
Classifier: Development Status :: 3 - Alpha
Classifier: License :: OSI Approved :: BSD License
Classifier: Programming Language :: Python
Classifier: Topic :: Internet :: WWW/HTTP :: WSGI :: Server
